ez_setup.py
pinnacle/__init__.py
pinnacle/pinnacle.py
pinnacle/plot_styles.py
pinnacle/pub_dataviz.py
pinnacle/user.py
pinnacle_pub-0.1.dist-info/LICENSE
pinnacle_pub-0.1.dist-info/METADATA
pinnacle_pub-0.1.dist-info/WHEEL
pinnacle_pub-0.1.dist-info/top_level.txt
pinnacle_pub-0.1.dist-info/RECORD
