Metadata-Version: 2.1
Name: pinnacle-pub
Version: 0.1
Summary: Tools to analyze publication metrics from an institution
Home-page: https://github.com/IATE-CONICET-UNC/pinnacle
Author: ['Marcelo Lares']
Author-email: marcelo.lares@unc.edu.ar
License: MIT
Keywords: publications
Platform: UNKNOWN
Classifier: Development Status :: 4 - Beta
Classifier: Intended Audience :: Education
Classifier: Intended Audience :: Science/Research
Classifier: License :: OSI Approved :: MIT License
Classifier: Operating System :: OS Independent
Classifier: Programming Language :: Python
Classifier: Programming Language :: Python :: 3.8
Classifier: Programming Language :: Python :: Implementation :: CPython
Classifier: Topic :: Scientific/Engineering
Requires-Dist: ads
Requires-Dist: numpy
Requires-Dist: pandas
Requires-Dist: pytest
Requires-Dist: openpyxl
